pybind_sdot_3d_double.cpython-36m-x86_64-linux-gnu.so
pybind_sdot_Arfd.cpython-36m-x86_64-linux-gnu.so
pybind_sdot_2d_double.cpython-36m-x86_64-linux-gnu.so
pysdot-0.2.16.dist-info/METADATA
pysdot-0.2.16.dist-info/top_level.txt
pysdot-0.2.16.dist-info/RECORD
pysdot-0.2.16.dist-info/WHEEL
pysdot/__init__.py
pysdot/TransportMap.py
pysdot/PowerDiagram.py
pysdot/OptimalTransport.py
pysdot/radial_funcs/RadialFuncUnit.py
pysdot/radial_funcs/RadialFuncEntropy.py
pysdot/radial_funcs/RadialFuncArfd.py
pysdot/radial_funcs/RadialFuncR2.py
pysdot/radial_funcs/__init__.py
pysdot/radial_funcs/RadialFuncPpWmR2.py
pysdot/radial_funcs/RadialFuncInBall.py
pysdot/domain_types/__init__.py
pysdot/domain_types/ScaledImage.py
pysdot/domain_types/ConvexPolyhedraAssembly.py
pysdot/util/__init__.py
pysdot/util/FastMarching.py
pysdot/solvers/CuPyx.py
pysdot/solvers/__init__.py
pysdot/solvers/Petsc.py
pysdot/solvers/Scipy.py
pysdot/cpp/pybind_sdot_Arfd.cpp
pysdot/cpp/pybind_sdot.cpp
pysdot/cpp/__init__.py
pysdot/cpp/inferno_color_map.h
pysdot/cpp/comb_types.h
pysdot/cpp/cpp_module.py
