Metadata-Version: 2.1
Name: pysdot
Version: 0.2.16
Summary: Semi-discrete operationnal transport
Home-page: https://github.com/sd-ot/sdot
Author: Hugo Leclerc
Author-email: hugal.leclerc@gmail.com
License: UNKNOWN
Platform: UNKNOWN
Classifier: Programming Language :: Python :: 3
Classifier: License :: OSI Approved :: MIT License
Classifier: Operating System :: OS Independent
Requires-Dist: numpy
